adafruit_ble_broadcastnet.py
adafruit_circuitpython_ble_broadcastnet-0.12.16.dist-info/licenses/LICENSE
adafruit_circuitpython_ble_broadcastnet-0.12.16.dist-info/METADATA
adafruit_circuitpython_ble_broadcastnet-0.12.16.dist-info/WHEEL
adafruit_circuitpython_ble_broadcastnet-0.12.16.dist-info/top_level.txt
adafruit_circuitpython_ble_broadcastnet-0.12.16.dist-info/RECORD
